steganon/__init__.py
steganon/api.py
steganon/errors.py
steganon/tools.py
steganon/version.py
steganon/cli/__init__.py
steganon/cli/steganon_cli.py
steganon/cli/tools.py
steganon-1.1.dist-info/licenses/LICENSE
steganon-1.1.dist-info/METADATA
steganon-1.1.dist-info/WHEEL
steganon-1.1.dist-info/entry_points.txt
steganon-1.1.dist-info/top_level.txt
steganon-1.1.dist-info/RECORD
