Metadata-Version: 2.4
Name: steganon
Version: 1.1
Summary: LSB Matching Steganography with PRNG & Deniable Hide
Home-page: https://github.com/NonProjects/steganon
Author: NonProjects
Author-email: thenonproton@pm.me
License: LGPL-2.1
Keywords: Steganography,LSB,Cryptography
Classifier: Intended Audience :: Developers
Classifier: Topic :: Security :: Cryptography
Classifier: License :: OSI Approved :: GNU General Public License v2 (GPLv2)
License-File: LICENSE
Requires-Dist: pillow
Provides-Extra: cli
Requires-Dist: click==8.1.7; extra == "cli"
Dynamic: author
Dynamic: author-email
Dynamic: classifier
Dynamic: description
Dynamic: description-content-type
Dynamic: home-page
Dynamic: keywords
Dynamic: license
Dynamic: license-file
Dynamic: provides-extra
Dynamic: requires-dist
Dynamic: summary
